stfu/__init__.py
stfu/py.typed
stfu-1.3.dist-info/METADATA
stfu-1.3.dist-info/WHEEL
stfu-1.3.dist-info/RECORD
